mooshak2api/__init__.py
mooshak2api/contests.py
mooshak2api/evaluation.py
mooshak2api/factory.py
mooshak2api/problems.py
mooshak2api/user.py
mooshak2api-0.1.0.dist-info/LICENSE
mooshak2api-0.1.0.dist-info/METADATA
mooshak2api-0.1.0.dist-info/WHEEL
mooshak2api-0.1.0.dist-info/top_level.txt
mooshak2api-0.1.0.dist-info/RECORD
