Metadata-Version: 2.1
Name: mooshak2api
Version: 0.1.0
Summary: A Python API for interacting with the Mooshak 2 REST API
Home-page: https://github.com/vCra/mooshak2api
Author: Aaron Walker
Author-email: aaw13@aber.ac.uk
License: MIT
Platform: UNKNOWN
Classifier: Development Status :: 2 - Pre-Alpha
Classifier: License :: OSI Approved :: MIT License
Classifier: Programming Language :: Python
Classifier: Programming Language :: Python :: 3
Classifier: Programming Language :: Python :: 3.4
Classifier: Programming Language :: Python :: 3.5
Classifier: Programming Language :: Python :: 3.6
Classifier: Programming Language :: Python :: 3.7
Requires-Dist: requests
